xpander_sdk/__init__.py
xpander_sdk/py.typed
xpander_sdk/_jsii/__init__.py
xpander_sdk/_jsii/xpander-sdk@1.1.2.jsii.tgz
xpander_ai-1.1.2.dist-info/LICENSE
xpander_ai-1.1.2.dist-info/METADATA
xpander_ai-1.1.2.dist-info/WHEEL
xpander_ai-1.1.2.dist-info/top_level.txt
xpander_ai-1.1.2.dist-info/RECORD
