Metadata-Version: 2.1
Name: xpander-ai
Version: 1.1.2
Summary: xpander-sdk
Home-page: https://github.com/xpander-ai/xpander-sdk.git
Author: xpander AI<opensource@xpander.ai>
License: Apache-2.0
Project-URL: Source, https://github.com/xpander-ai/xpander-sdk.git
Classifier: Intended Audience :: Developers
Classifier: Operating System :: OS Independent
Classifier: Programming Language :: JavaScript
Classifier: Programming Language :: Python :: 3 :: Only
Classifier: Programming Language :: Python :: 3.8
Classifier: Programming Language :: Python :: 3.9
Classifier: Programming Language :: Python :: 3.10
Classifier: Programming Language :: Python :: 3.11
Classifier: Typing :: Typed
Classifier: Development Status :: 5 - Production/Stable
Classifier: License :: OSI Approved
Requires-Python: ~=3.8
License-File: LICENSE
Requires-Dist: jsii<2.0.0,>=1.103.1
Requires-Dist: publication>=0.0.3
Requires-Dist: typeguard<5.0.0,>=2.13.3
